mongodesu/__init__.py
mongodesu/mongolib.py
mongodesu/fields/__init__.py
mongodesu/fields/base.py
mongodesu/fields/types.py
mongodesu/serializable/__init__.py
mongodesu/serializable/serializable.py
mongodesu-2.0.2.dist-info/licenses/LICENSE
mongodesu-2.0.2.dist-info/METADATA
mongodesu-2.0.2.dist-info/WHEEL
mongodesu-2.0.2.dist-info/top_level.txt
mongodesu-2.0.2.dist-info/RECORD
