Metadata-Version: 2.4
Name: mongodesu
Version: 2.0.2
Summary: A mongodb ODM dependant on pymongo with extensive model creation, validation, and relational model mechanism.
Author-email: Akuyaku <babai.akuyaku@gmail.com>
License: MIT
Project-URL: Homepage, https://github.com/AKA-Per/mongudesu
Requires-Python: >=3.8
License-File: LICENSE
Requires-Dist: pymongo==4.8.0
Requires-Dist: inflect==7.3.1
Requires-Dist: python-dateutil==2.7.3
Dynamic: license-file
